line.py
count_linellw-0.1.2.dist-info/LICENSE
count_linellw-0.1.2.dist-info/METADATA
count_linellw-0.1.2.dist-info/WHEEL
count_linellw-0.1.2.dist-info/entry_points.txt
count_linellw-0.1.2.dist-info/top_level.txt
count_linellw-0.1.2.dist-info/RECORD
