Metadata-Version: 2.1
Name: count-linellw
Version: 0.1.2
Summary: A command line tool to count lines and files numbers under current directory.
Home-page: https://github.com/1438723338/count-line
Author: 1438723338
Author-email: 1438723338@qq.com
License: MIT
Classifier: License :: OSI Approved :: MIT License
Classifier: Programming Language :: Python
Classifier: Programming Language :: Python :: 3
Classifier: Programming Language :: Python :: 3.6
Classifier: Programming Language :: Python :: Implementation :: CPython
Classifier: Programming Language :: Python :: Implementation :: PyPy
Requires-Python: >=3
License-File: LICENSE
